pyvispr/__init__.py
pyvispr/generic.py
pyvispr/install.py
pyvispr/run.py
pyvispr/version.py
pyvispr/catalog/installer.py
pyvispr/catalog/parser.py
pyvispr/catalog/type.py
pyvispr/catalog/factory/_expression_evaluator.py
pyvispr/catalog/factory/expression_evaluator.py
pyvispr/catalog/factory/control/for_each.py
pyvispr/catalog/factory/control/if_branch.py
pyvispr/catalog/factory/control/if_choice.py
pyvispr/catalog/factory/control/loop_for.py
pyvispr/catalog/factory/control/loop_start.py
pyvispr/catalog/factory/control/loop_while.py
pyvispr/catalog/factory/control/pause.py
pyvispr/catalog/factory/data/data_joiner.py
pyvispr/catalog/factory/data/data_splitter.py
pyvispr/catalog/factory/data/identity.py
pyvispr/catalog/factory/data/value.py
pyvispr/catalog/factory/data/value_printer.py
pyvispr/catalog/factory/data/value_viewer.py
pyvispr/catalog/factory/image/ann_segmenter.py
pyvispr/catalog/factory/image/loader.py
pyvispr/catalog/factory/image/saver.py
pyvispr/catalog/factory/image/viewer.py
pyvispr/config/constant.py
pyvispr/config/path.py
pyvispr/config/type.py
pyvispr/config/appearance/backend.py
pyvispr/config/appearance/behavior.py
pyvispr/config/appearance/color.py
pyvispr/config/appearance/geometry.py
pyvispr/constant/app.py
pyvispr/constant/catalog.py
pyvispr/constant/flow/node.py
pyvispr/constant/flow/uid.py
pyvispr/constant/flow/value.py
pyvispr/constant/interface/storage/path.py
pyvispr/constant/interface/widget/function_header.py
pyvispr/constant/interface/widget/list.py
pyvispr/constant/interface/widget/menu.py
pyvispr/constant/interface/widget/node.py
pyvispr/constant/interface/widget/whiteboard.py
pyvispr/exception/catalog.py
pyvispr/exception/graph.py
pyvispr/exception/link.py
pyvispr/exception/node.py
pyvispr/extension/introspection/function.py
pyvispr/extension/introspection/module.py
pyvispr/extension/object/field.py
pyvispr/extension/object/text.py
pyvispr/extension/object/type.py
pyvispr/extension/qt/app.py
pyvispr/extension/qt/graphics_view.py
pyvispr-2024.44.dist-info/METADATA
pyvispr-2024.44.dist-info/WHEEL
pyvispr-2024.44.dist-info/entry_points.txt
pyvispr-2024.44.dist-info/top_level.txt
pyvispr-2024.44.dist-info/RECORD
