Metadata-Version: 2.1
Name: pyvispr
Version: 2024.44
Summary: Visual Programming App for Python
Home-page: https://src.koda.cnrs.fr/eric.debreuve/pyvispr/
Author: Eric Debreuve
Author-email: eric.debreuve@cnrs.fr
License: CeCILL-2.1
Project-URL: Documentation, https://src.koda.cnrs.fr/eric.debreuve/pyvispr/-/wikis/home
Project-URL: Source, https://src.koda.cnrs.fr/eric.debreuve/pyvispr/
Keywords: Visual programming,Python
Classifier: Topic :: Scientific/Engineering
Classifier: Intended Audience :: Science/Research
Classifier: License :: OSI Approved :: CEA CNRS Inria Logiciel Libre License, version 2.1 (CeCILL-2.1)
Classifier: Programming Language :: Python :: 3
Classifier: Development Status :: 3 - Alpha
Requires-Python: >=3.11
Requires-Dist: babelwidget
Requires-Dist: conf-ini-g
Requires-Dist: json-any
Requires-Dist: logger-36
Requires-Dist: numpy
Requires-Dist: platformdirs
Requires-Dist: PyQt6
Requires-Dist: scikit-image
Requires-Dist: sio-messenger
Requires-Dist: str-to-obj
